image_extract_from_urls/__init__.py
image_extract_from_urls/__main__.py
Image_Extract_from_URLs-0.0.1.dist-info/LICENSE
Image_Extract_from_URLs-0.0.1.dist-info/METADATA
Image_Extract_from_URLs-0.0.1.dist-info/WHEEL
Image_Extract_from_URLs-0.0.1.dist-info/entry_points.txt
Image_Extract_from_URLs-0.0.1.dist-info/top_level.txt
Image_Extract_from_URLs-0.0.1.dist-info/RECORD
