Metadata-Version: 2.1
Name: Image_Extract_from_URLs
Version: 0.0.1
Summary: Downloading Images from the URLs in the txt file
Home-page: UNKNOWN
Author: Suriyakrishnan Sathish
License: UNKNOWN
Platform: UNKNOWN
License-File: LICENSE
